stockscraping/__init__.py
stockscraping/stockdata_scraper.py
stockscraping-0.2.4.dist-info/WHEEL
stockscraping-0.2.4.dist-info/METADATA
stockscraping-0.2.4.dist-info/RECORD
